sec_stream/__init__.py
sec_stream/stream.py
sec_stream/tickers.py
sec_stream-0.0.34.dist-info/LICENSE.txt
sec_stream-0.0.34.dist-info/METADATA
sec_stream-0.0.34.dist-info/WHEEL
sec_stream-0.0.34.dist-info/top_level.txt
sec_stream-0.0.34.dist-info/RECORD
