Metadata-Version: 2.1
Name: sec-stream
Version: 0.0.34
Summary: A package to scrape SEC data
Author: Noah Taylor
Author-email: nstaylor03@gmail.com
Keywords: python,sec,finance,requests
Classifier: Development Status :: 1 - Planning
Classifier: Intended Audience :: Developers
Classifier: Programming Language :: Python :: 3
Classifier: Operating System :: Unix
Classifier: Operating System :: MacOS :: MacOS X
Classifier: Operating System :: Microsoft :: Windows
License-File: LICENSE.txt
Requires-Dist: lxml
Requires-Dist: requests
Requires-Dist: beautifulsoup4
